sam/Sam.py
sam/__init__.py
sam/utils.py
sam_scraper-0.1.2.dist-info/LICENSE
sam_scraper-0.1.2.dist-info/METADATA
sam_scraper-0.1.2.dist-info/WHEEL
sam_scraper-0.1.2.dist-info/top_level.txt
sam_scraper-0.1.2.dist-info/RECORD
