Metadata-Version: 2.1
Name: sam-scraper
Version: 0.1.2
Summary: The `sam-scraper` is designed for seamless interaction with the sam.gov API,
Home-page: https://github.com/Diego-Arrechea/sam-scraper
Author: Diego Arrechea
Author-email: diego.arrechea.job@gmail.com
License: MIT
Requires-Python: >=3.6
License-File: LICENSE
Requires-Dist: requests
